{
  "name": "dappnodepackage-iexec-scheduler-db.public.dappnode.eth",
  "version": "0.0.1",
  "description": "Dappnode Package for iexec scheduler db",
  "avatar": "",
  "type": "service",
  "image": {
    "path": "",
    "hash": "",
    "size": "",
    "restart": "always",
    "volumes": [
      "iexecschedulerdb:/data/db"
    ],
    "ports": [
      "27017:27017"
    ],
    "keywords": [
      "IEXEC",
      "SCHEDULER",
      "DB"
    ]
  },
  "author": "francois branciard",
  "license": "",
  "dependencies": {}
}